{
  "id":null,
  "version":null,
  "responsetime":"2019-08-26T06:46:04.089Z",
  "metadata":null,
  "response":{
    "lastSyncTime":"2019-08-26T06:46:04.066Z",
    "userDetails":[
      {
        "isDeleted":null,
        "langCode":null,
        "isActive":null,
        "userName":"110001",
        "mail":"sravya.surampalli@mindtree.com",
        "mobile":"9989636932",
        "userPassword":"493ADAF78608AE4332F513E58D894360BFFC845B15EF036C3F7B4E9374925655",
        "name":"test",
        "roles":[
          "REGISTRATION_ADMIN",
          "REGISTRATION_OFFICER",
          "ZONAL_ADMIN",
          "REGISTRATION_SUPERVISOR"],
        "rid":null
      },
      {
        "isDeleted":null,
        "langCode":null,
        "isActive":null,
        "userName":"110030",
        "mail":"sagar.mahapatra2@mindtree.com",
        "mobile":"7504871938",
        "userPassword":"45668BE9522D30821A556C5AB6A4C989BF5A9F3D087477F8BBF1F48633D42F2C",
        "name":"ridtest",
        "roles":[
          "ZONAL_ADMIN"],
        "rid":null
      }]
  },
  "errors":null
}